Mathexs
