Metadata-Version: 2.1
Name: Mathexs
Version: 0.0.2
Summary: More functions added
Home-page: 
Author: Adem Rebahi
Author-email: ademlp2012@gmail.com
License: MIT
Keywords: Functions,Advenced,Drawer_Shaper
Classifier: Development Status :: 5 - Production/Stable
Classifier: Intended Audience :: Education
Classifier: Operating System :: Microsoft :: Windows :: Windows 10
Classifier: License :: OSI Approved :: MIT License
Classifier: Programming Language :: Python :: 3
License-File: LICENSE.txt
